kapso/__init__.py
kapso/cli.py
kapso/config.yaml
kapso/kapso.py
kapso/core/__init__.py
kapso/core/config.py
kapso/core/llm.py
kapso/core/prompt_loader.py
kapso/deployment/__init__.py
kapso/deployment/base.py
kapso/deployment/factory.py
kapso/deployment/software.py
kapso/deployment/adapter/__init__.py
kapso/deployment/adapter/adaptation_prompt.txt
kapso/deployment/adapter/agent.py
kapso/deployment/adapter/validator.py
kapso/deployment/selector/agent.py
kapso/deployment/selector/correction_prompt.md
kapso/deployment/selector/selection_prompt.md
kapso/deployment/strategies/README.md
kapso/deployment/strategies/__init__.py
kapso/deployment/strategies/base.py
kapso/deployment/strategies/bentoml/__init__.py
kapso/deployment/strategies/bentoml/adapter_instruction.txt
kapso/deployment/strategies/bentoml/config.yaml
kapso/deployment/strategies/bentoml/runner.py
kapso/deployment/strategies/bentoml/selector_instruction.txt
kapso/deployment/strategies/docker/__init__.py
kapso/deployment/strategies/docker/adapter_instruction.txt
kapso/deployment/strategies/docker/config.yaml
kapso/deployment/strategies/docker/runner.py
kapso/deployment/strategies/docker/selector_instruction.txt
kapso/deployment/strategies/langgraph/__init__.py
kapso/deployment/strategies/langgraph/adapter_instruction.txt
kapso/deployment/strategies/langgraph/config.yaml
kapso/deployment/strategies/langgraph/runner.py
kapso/deployment/strategies/langgraph/selector_instruction.txt
kapso/deployment/strategies/local/__init__.py
kapso/deployment/strategies/local/adapter_instruction.txt
kapso/deployment/strategies/local/config.yaml
kapso/deployment/strategies/local/runner.py
kapso/deployment/strategies/local/selector_instruction.txt
kapso/deployment/strategies/modal/__init__.py
kapso/deployment/strategies/modal/adapter_instruction.txt
kapso/deployment/strategies/modal/config.yaml
kapso/deployment/strategies/modal/runner.py
kapso/deployment/strategies/modal/selector_instruction.txt
kapso/environment/__init__.py
leeroo_kapso-0.1.1.dist-info/licenses/LICENSE
leeroo_kapso-0.1.1.dist-info/METADATA
leeroo_kapso-0.1.1.dist-info/WHEEL
leeroo_kapso-0.1.1.dist-info/entry_points.txt
leeroo_kapso-0.1.1.dist-info/top_level.txt
leeroo_kapso-0.1.1.dist-info/RECORD
