Metadata-Version: 2.4
Name: leeroo-kapso
Version: 0.1.1
Summary: A Knowledge-grounded framework for Autonomous Program Synthesis and Optimization
Author-email: Leeroo Team <team@leeroo.com>
License: MIT
Project-URL: Homepage, https://leeroo.com
Project-URL: Documentation, https://docs.leeroo.com
Project-URL: Repository, https://github.com/leeroo-ai/kapso
Project-URL: Issues, https://github.com/leeroo-ai/kapso/issues
Keywords: ai,ml,optimization,code-generation,llm,agents
Classifier: Development Status :: 4 - Beta
Classifier: Intended Audience :: Developers
Classifier: Intended Audience :: Science/Research
Classifier: License :: OSI Approved :: MIT License
Classifier: Programming Language :: Python :: 3
Classifier: Programming Language :: Python :: 3.10
Classifier: Programming Language :: Python :: 3.11
Classifier: Programming Language :: Python :: 3.12
Classifier: Topic :: Scientific/Engineering :: Artificial Intelligence
Requires-Python: >=3.10
License-File: LICENSE
Requires-Dist: GitPython
Requires-Dist: aider-chat>=0.35.0
Requires-Dist: PyYAML
Requires-Dist: python-dotenv
Requires-Dist: neo4j
Requires-Dist: weaviate-client>=4.0.0
Requires-Dist: openai>=1.0.0
Requires-Dist: cryptography<46.0.0
Provides-Extra: mle
Requires-Dist: neo4j; extra == "mle"
Requires-Dist: openai; extra == "mle"
Provides-Extra: ale
Provides-Extra: dev
Requires-Dist: pytest>=7.0.0; extra == "dev"
Requires-Dist: pytest-cov>=4.0.0; extra == "dev"
Requires-Dist: black>=23.0.0; extra == "dev"
Requires-Dist: flake8>=6.0.0; extra == "dev"
Dynamic: license-file
